amazon_sagemaker_sql_execution/__init__.py
amazon_sagemaker_sql_execution/connection.py
amazon_sagemaker_sql_execution/connection_pool.py
amazon_sagemaker_sql_execution/exceptions.py
amazon_sagemaker_sql_execution/sql_connection_supplier.py
amazon_sagemaker_sql_execution/athena/__init__.py
amazon_sagemaker_sql_execution/athena/connection.py
amazon_sagemaker_sql_execution/athena/connection_supplier.py
amazon_sagemaker_sql_execution/athena/models.py
amazon_sagemaker_sql_execution/models/__init__.py
amazon_sagemaker_sql_execution/models/sql_execution.py
amazon_sagemaker_sql_execution/redshift/__init__.py
amazon_sagemaker_sql_execution/redshift/connection.py
amazon_sagemaker_sql_execution/redshift/connection_supplier.py
amazon_sagemaker_sql_execution/redshift/models.py
amazon_sagemaker_sql_execution/snowflake/__init__.py
amazon_sagemaker_sql_execution/snowflake/connection.py
amazon_sagemaker_sql_execution/snowflake/connection_supplier.py
amazon_sagemaker_sql_execution/snowflake/models.py
amazon_sagemaker_sql_execution/utils/__init__.py
amazon_sagemaker_sql_execution/utils/aws_secret_retriver.py
amazon_sagemaker_sql_execution/utils/constants.py
amazon_sagemaker_sql_execution/utils/logging_utils.py
amazon_sagemaker_sql_execution/utils/mixins.py
amazon_sagemaker_sql_execution/utils/sql_connection_factory.py
amazon_sagemaker_sql_execution/utils/sql_connection_supplier_factory.py
amazon_sagemaker_sql_execution/utils/metadata_retriever/BaseSQLFactory.py
amazon_sagemaker_sql_execution/utils/metadata_retriever/__init__.py
amazon_sagemaker_sql_execution/utils/metadata_retriever/connection_metadata_retriever.py
amazon_sagemaker_sql_execution/utils/metadata_retriever/file_metadata_retriever.py
amazon_sagemaker_sql_execution/utils/metadata_retriever/glueconnection_metadata_retriever.py
amazon_sagemaker_sql_execution/utils/metadata_retriever/metadata_retriever_factory.py
amazon_sagemaker_sql_execution/utils/metrics/__init__.py
amazon_sagemaker_sql_execution-0.1.5.dist-info/LICENSE
amazon_sagemaker_sql_execution-0.1.5.dist-info/METADATA
amazon_sagemaker_sql_execution-0.1.5.dist-info/WHEEL
amazon_sagemaker_sql_execution-0.1.5.dist-info/top_level.txt
amazon_sagemaker_sql_execution-0.1.5.dist-info/RECORD
