Metadata-Version: 2.1
Name: amazon-sagemaker-sql-execution
Version: 0.1.5
Summary: SageMaker SQL Execution library
Author: Amazon Web Services
License: 
Project-URL: homepage, https://aws.amazon.com/sagemaker
Classifier: Intended Audience :: Developers
Classifier: Intended Audience :: Science/Research
Classifier: License :: OSI Approved :: Apache Software License
Classifier: Programming Language :: Python
Classifier: Programming Language :: Python :: 3.8
Classifier: Programming Language :: Python :: 3.9
Classifier: Programming Language :: Python :: 3.10
Classifier: Programming Language :: Python :: 3.11
Requires-Python: >=3.8
License-File: LICENSE
Requires-Dist: boto3>=1.28.64
Requires-Dist: pyathena<4,>=3.3.0
Requires-Dist: redshift-connector<3,>=2.1.0
Requires-Dist: aws_embedded_metrics<4,>=3.2.0
Requires-Dist: snowflake-connector-python<4.0,>=3.8.1
Requires-Dist: cryptography>=42.0.0
Provides-Extra: all
Requires-Dist: amazon-sagemaker-sql-execution[dev,flake8,pydocstyle,pylint,snowflake,test,twine]; extra == "all"
Provides-Extra: snowflake
Requires-Dist: snowflake-connector-python<4.0,>=3.7.0; extra == "snowflake"
Provides-Extra: dev
Requires-Dist: black; extra == "dev"
Requires-Dist: build; extra == "dev"
Provides-Extra: test
Requires-Dist: snowflake-connector-python<4.0,>=3.7.0; extra == "test"
Requires-Dist: pytest; extra == "test"
Requires-Dist: tox==4.11.4; extra == "test"
Requires-Dist: parameterized; extra == "test"
Requires-Dist: coverage; extra == "test"
Requires-Dist: pytest-cov; extra == "test"
Requires-Dist: pytest-timeout; extra == "test"
Provides-Extra: flake8
Requires-Dist: flake8==4.0.1; extra == "flake8"
Requires-Dist: flake8-future-import==0.4.6; extra == "flake8"
Provides-Extra: pylint
Requires-Dist: pylint==2.6.2; extra == "pylint"
Requires-Dist: astroid==2.4.2; extra == "pylint"
Provides-Extra: pydocstyle
Requires-Dist: pydocstyle==6.1.1; extra == "pydocstyle"
Provides-Extra: twine
Requires-Dist: twine==3.8.0; extra == "twine"
Requires-Dist: packaging; extra == "twine"
